{"name":"Brass Dragon Wyrmling","size":"Medium","type":"dragon","subtype":"","alignment":"chaotic good","armor_class":16,"hit_points":16,"hit_dice":"3d8","speed":"30 ft., burrow 15 ft., fly 60 ft.","strength":15,"dexterity":10,"constitution":13,"intelligence":10,"wisdom":11,"charisma":13,"dexterity_save":2,"constitution_save":3,"wisdom_save":2,"charisma_save":3,"perception":4,"stealth":2,"damage_vulnerabilities":"","damage_resistances":"","damage_immunities":"fire","condition_immunities":"","senses":"blindsight 10 ft., darkvision 60 ft., passive Perception 14","languages":"Draconic","challenge_rating":"1","actions":[{"name":"Bite","desc":"Melee Weapon Attack: +4 to hit, reach 5 ft., one target. Hit: 7 (1d10 + 2) piercing damage.","attack_bonus":4,"damage_dice":"1d10","damage_bonus":2},{"name":"Breath Weapons (Recharge 5-6)","desc":"The dragon uses one of the following breath weapons.\nFire Breath. The dragon exhales fire in an 20-foot line that is 5 feet wide. Each creature in that line must make a DC 11 Dexterity saving throw, taking 14 (4d6) fire damage on a failed save, or half as much damage on a successful one.\nSleep Breath. The dragon exhales sleep gas in a 15-foot cone. Each creature in that area must succeed on a DC 11 Constitution saving throw or fall unconscious for 1 minute. This effect ends for a creature if the creature takes damage or someone uses an action to wake it.","attack_bonus":0,"damage_dice":"4d6"}],"speed_json":{"walk":30,"burrow":15,"fly":60}}
