{"name":"Swarm of Rats","size":"Medium","type":"swarm of Tiny beasts","subtype":"","alignment":"unaligned","armor_class":10,"hit_points":24,"hit_dice":"7d8","speed":"30 ft.","strength":9,"dexterity":11,"constitution":9,"intelligence":2,"wisdom":10,"charisma":3,"damage_vulnerabilities":"","damage_resistances":"bludgeoning, piercing, slashing","damage_immunities":"","condition_immunities":"charmed, frightened, grappled, paralyzed, petrified, prone, restrained, stunned","senses":"darkvision 30 ft., passive Perception 10","languages":"","challenge_rating":"1/4","special_abilities":[{"name":"Keen Smell","desc":"The swarm has advantage on Wisdom (Perception) checks that rely on smell.","attack_bonus":0},{"name":"Swarm","desc":"The swarm can occupy another creature's space and vice versa, and the swarm can move through any opening large enough for a Tiny rat. The swarm can't regain hit points or gain temporary hit points.","attack_bonus":0}],"actions":[{"name":"Bites","desc":"Melee Weapon Attack: +2 to hit, reach 0 ft., one target in the swarm's space. Hit: 7 (2d6) piercing damage, or 3 (1d6) piercing damage if the swarm has half of its hit points or fewer.","attack_bonus":2,"damage_dice":"2d6"}],"speed_json":{"walk":30}}
